openenergyid/__init__.py
openenergyid/const.py
openenergyid/enums.py
openenergyid/models.py
openenergyid/abstractsim/__init__.py
openenergyid/abstractsim/abstract.py
openenergyid/baseload/__init__.py
openenergyid/baseload/analysis.py
openenergyid/baseload/exceptions.py
openenergyid/baseload/models.py
openenergyid/capacity/__init__.py
openenergyid/capacity/main.py
openenergyid/capacity/models.py
openenergyid/dyntar/__init__.py
openenergyid/dyntar/const.py
openenergyid/dyntar/main.py
openenergyid/dyntar/models.py
openenergyid/elia/__init__.py
openenergyid/elia/api.py
openenergyid/elia/const.py
openenergyid/energysharing/__init__.py
openenergyid/energysharing/const.py
openenergyid/energysharing/data_formatting.py
openenergyid/energysharing/main.py
openenergyid/energysharing/models.py
openenergyid/mvlr/__init__.py
openenergyid/mvlr/helpers.py
openenergyid/mvlr/main.py
openenergyid/mvlr/models.py
openenergyid/mvlr/mvlr.py
openenergyid/pvsim/__init__.py
openenergyid/pvsim/abstract.py
openenergyid/pvsim/main.py
openenergyid/pvsim/elia/__init__.py
openenergyid/pvsim/elia/main.py
openenergyid/pvsim/pvlib/__init__.py
openenergyid/pvsim/pvlib/main.py
openenergyid/pvsim/pvlib/models.py
openenergyid/pvsim/pvlib/quickscan.py
openenergyid/pvsim/pvlib/weather.py
openenergyid/sim/__init__.py
openenergyid/sim/main.py
openenergyid/simeval/__init__.py
openenergyid/simeval/main.py
openenergyid/simeval/models.py
openenergyid-0.1.33.dist-info/licenses/LICENSE
openenergyid-0.1.33.dist-info/METADATA
openenergyid-0.1.33.dist-info/WHEEL
openenergyid-0.1.33.dist-info/top_level.txt
openenergyid-0.1.33.dist-info/RECORD
