Metadata-Version: 2.4
Name: openenergyid
Version: 0.1.33
Summary: Open Source Python library for energy analytics and simulations
Author-email: Jan Pecinovsky <jan@energieid.be>, Max Helskens <max@energieid.be>, Oscar Swyns <oscar@energieid.be>
License-Expression: MIT
Keywords: energy,analytics,simulation
Classifier: Development Status :: 3 - Alpha
Classifier: Intended Audience :: Developers
Classifier: Intended Audience :: Science/Research
Classifier: Natural Language :: English
Classifier: Operating System :: OS Independent
Classifier: Programming Language :: Python :: 3
Classifier: Topic :: Scientific/Engineering
Classifier: Topic :: Scientific/Engineering :: Mathematics
Classifier: Topic :: Scientific/Engineering :: Physics
Classifier: Topic :: Software Development :: Libraries :: Python Modules
Requires-Python: >=3.11
License-File: LICENSE
Requires-Dist: aiohttp>=3.12.15
Requires-Dist: pandera[polars]>=0.22.1
Requires-Dist: pvlib>=0.13.0
Requires-Dist: pydantic>=2.8.2
Requires-Dist: statsmodels>=0.14.2
Dynamic: license-file
